MANIFEST.in
README.rst
setup.py
docs/HISTORY.txt
docs/LICENSE.GPL
docs/LICENSE.txt
ftw/__init__.py
ftw.logo.egg-info/PKG-INFO
ftw.logo.egg-info/SOURCES.txt
ftw.logo.egg-info/dependency_links.txt
ftw.logo.egg-info/entry_points.txt
ftw.logo.egg-info/namespace_packages.txt
ftw.logo.egg-info/not-zip-safe
ftw.logo.egg-info/requires.txt
ftw.logo.egg-info/top_level.txt
ftw/logo/StringIOStreamIterator.py
ftw/logo/__init__.py
ftw/logo/configure.zcml
ftw/logo/converter.py
ftw/logo/image.py
ftw/logo/interfaces.py
ftw/logo/lawgiver.zcml
ftw/logo/logo.py
ftw/logo/logoconfig.py
ftw/logo/manual_override.pt
ftw/logo/manual_override.py
ftw/logo/manual_override_view.pt
ftw/logo/meta.py
ftw/logo/meta.zcml
ftw/logo/permissions.zcml
ftw/logo/resources.zcml
ftw/logo/testing.py
ftw/logo/Extensions/__init__.py
ftw/logo/Extensions/install.py
ftw/logo/browser/__init__.py
ftw/logo/browser/browserconfig_view.py
ftw/logo/browser/configure.zcml
ftw/logo/browser/icon_viewlet.pt
ftw/logo/browser/icon_viewlet.py
ftw/logo/browser/logo_base_viewlet.py
ftw/logo/browser/logo_view.py
ftw/logo/browser/logo_viewlet.pt
ftw/logo/browser/logo_viewlet.py
ftw/logo/browser/webmanifest_view.py
ftw/logo/locales/ftw.logo.pot
ftw/logo/locales/plone.pot
ftw/logo/locales/de/LC_MESSAGES/ftw.logo.po
ftw/logo/locales/de/LC_MESSAGES/plone.po
ftw/logo/profiles/caching/metadata.xml
ftw/logo/profiles/caching/registry.xml
ftw/logo/profiles/default/actions.xml
ftw/logo/profiles/default/browserlayer.xml
ftw/logo/profiles/default/metadata.xml
ftw/logo/profiles/default/propertiestool.xml
ftw/logo/profiles/default/rolemap.xml
ftw/logo/profiles/default/types.xml
ftw/logo/profiles/default/types/ftw.logo.ManualOverrides.xml
ftw/logo/profiles/default_plone5/actions.xml
ftw/logo/profiles/default_plone5/browserlayer.xml
ftw/logo/profiles/default_plone5/metadata.xml
ftw/logo/profiles/default_plone5/rolemap.xml
ftw/logo/profiles/default_plone5/types.xml
ftw/logo/profiles/default_plone5/types/ftw.logo.ManualOverrides.xml
ftw/logo/profiles/uninstall/actions.xml
ftw/logo/profiles/uninstall/browserlayer.xml
ftw/logo/profiles/uninstall/propertiestool.xml
ftw/logo/profiles/uninstall/rolemap.xml
ftw/logo/profiles/uninstall/types.xml
ftw/logo/profiles/uninstall_plone5/actions.xml
